LibEER/ACRNN_train.py
LibEER/CDCN_train.py
LibEER/DBN_train.py
LibEER/DGCNN_train.py
LibEER/EEGNet_train.py
LibEER/GCBNet_BLS_train.py
LibEER/GCBNet_train.py
LibEER/HSLT_train.py
LibEER/Msmda_train.py
LibEER/RGNN_train.py
LibEER/TSception_train.py
LibEER/__init__.py
LibEER/generate.py
LibEER/main.py
LibEER/svm_train.py
LibEER/test.py
LibEER/test_device.py
LibEER/Trainer/DBNTraining.py
LibEER/Trainer/MsMdaTraining.py
LibEER/Trainer/__init__.py
LibEER/Trainer/graphTraining.py
LibEER/Trainer/training.py
LibEER/config/__init__.py
LibEER/config/setting.py
LibEER/data_utils/__init__.py
LibEER/data_utils/clean_asr.py
LibEER/data_utils/load_data.py
LibEER/data_utils/preprocess.py
LibEER/data_utils/split.py
LibEER/models/ACRNN.py
LibEER/models/CDCN.py
LibEER/models/DBN.py
LibEER/models/DGCNN.py
LibEER/models/EEGNet.py
LibEER/models/GCBNet.py
LibEER/models/GCBNet_BLS.py
LibEER/models/HSLT.py
LibEER/models/Models.py
LibEER/models/MsMda.py
LibEER/models/RGNN.py
LibEER/models/RGNN_official.py
LibEER/models/STRNN.py
LibEER/models/SVM.py
LibEER/models/TSception.py
LibEER/models/__init__.py
LibEER/utils/__init__.py
LibEER/utils/args.py
LibEER/utils/metric.py
LibEER/utils/store.py
LibEER/utils/utils.py
LibEER-0.1.4.dist-info/METADATA
LibEER-0.1.4.dist-info/WHEEL
LibEER-0.1.4.dist-info/top_level.txt
LibEER-0.1.4.dist-info/RECORD
